scripts/__init__.py
scripts/wptool.py
wptools/__init__.py
wptools/category.py
wptools/core.py
wptools/page.py
wptools/query.py
wptools/request.py
wptools/restbase.py
wptools/site.py
wptools/utils.py
wptools/wikidata.py
wptools-0.4.17.dist-info/DESCRIPTION.rst
wptools-0.4.17.dist-info/METADATA
wptools-0.4.17.dist-info/RECORD
wptools-0.4.17.dist-info/WHEEL
wptools-0.4.17.dist-info/entry_points.txt
wptools-0.4.17.dist-info/metadata.json
wptools-0.4.17.dist-info/top_level.txt
