Metadata-Version: 1.1
Name: wptools
Version: 0.4.17
Summary: Wikipedia tools (for Humans)
Home-page: https://github.com/siznax/wptools/
Author: Steve @siznax
Author-email: steve@siznax.net
License: MIT
Platform: UNKNOWN
Classifier: Development Status :: 3 - Alpha
Classifier: Intended Audience :: Developers
Classifier: Intended Audience :: Education
Classifier: Intended Audience :: Science/Research
Classifier: License :: OSI Approved :: MIT License
Classifier: Operating System :: OS Independent
Classifier: Programming Language :: Python
Classifier: Programming Language :: Python :: 2.7
Classifier: Programming Language :: Python :: 3
